huaweicloudsdkimagesearch/__init__.py
huaweicloudsdkimagesearch/v2/__init__.py
huaweicloudsdkimagesearch/v2/imagesearch_async_client.py
huaweicloudsdkimagesearch/v2/imagesearch_client.py
huaweicloudsdkimagesearch/v2/model/__init__.py
huaweicloudsdkimagesearch/v2/model/add_data_optional_param.py
huaweicloudsdkimagesearch/v2/model/add_data_param.py
huaweicloudsdkimagesearch/v2/model/add_data_rest_info.py
huaweicloudsdkimagesearch/v2/model/add_data_rest_info_image_info.py
huaweicloudsdkimagesearch/v2/model/add_data_rest_info_image_info_objects.py
huaweicloudsdkimagesearch/v2/model/check_info.py
huaweicloudsdkimagesearch/v2/model/check_param.py
huaweicloudsdkimagesearch/v2/model/check_rest_info.py
huaweicloudsdkimagesearch/v2/model/delete_info.py
huaweicloudsdkimagesearch/v2/model/delete_param.py
huaweicloudsdkimagesearch/v2/model/delete_rest_info.py
huaweicloudsdkimagesearch/v2/model/delete_rest_info_items.py
huaweicloudsdkimagesearch/v2/model/item_source.py
huaweicloudsdkimagesearch/v2/model/range_param.py
huaweicloudsdkimagesearch/v2/model/run_add_data_request.py
huaweicloudsdkimagesearch/v2/model/run_add_data_response.py
huaweicloudsdkimagesearch/v2/model/run_check_data_request.py
huaweicloudsdkimagesearch/v2/model/run_check_data_response.py
huaweicloudsdkimagesearch/v2/model/run_delete_data_request.py
huaweicloudsdkimagesearch/v2/model/run_delete_data_response.py
huaweicloudsdkimagesearch/v2/model/run_search_request.py
huaweicloudsdkimagesearch/v2/model/run_search_response.py
huaweicloudsdkimagesearch/v2/model/run_update_data_request.py
huaweicloudsdkimagesearch/v2/model/run_update_data_response.py
huaweicloudsdkimagesearch/v2/model/search_after_param.py
huaweicloudsdkimagesearch/v2/model/search_info.py
huaweicloudsdkimagesearch/v2/model/search_item.py
huaweicloudsdkimagesearch/v2/model/search_optional_param.py
huaweicloudsdkimagesearch/v2/model/search_param.py
huaweicloudsdkimagesearch/v2/model/search_rest_info.py
huaweicloudsdkimagesearch-3.1.184.dist-info/METADATA
huaweicloudsdkimagesearch-3.1.184.dist-info/WHEEL
huaweicloudsdkimagesearch-3.1.184.dist-info/licenses/LICENSE
huaweicloudsdkimagesearch-3.1.184.dist-info/RECORD
